env_minion/__init__.py
env_minion/hook_factory.py
env_minion/pre-push.txt
env_minion-0.0.5.dist-info/LICENSE
env_minion-0.0.5.dist-info/METADATA
env_minion-0.0.5.dist-info/WHEEL
env_minion-0.0.5.dist-info/entry_points.txt
env_minion-0.0.5.dist-info/top_level.txt
env_minion-0.0.5.dist-info/RECORD
