Metadata-Version: 2.1
Name: env-minion
Version: 0.0.5
Summary: Enforces environmental variable conformance with template shared across team
Home-page: https://github.com/NikaEco/env-minion
Author: Nisemono
License-File: LICENSE
